<annotation>
  <folder>train</folder>
  <filename>100.jpg</filename>
  <path>../images/100.jpg</path>
  <source>
    <database>flowchart_3b_v3</database>
  </source>
  <size>
    <width>2992</width>
    <height>4000</height>
    <depth>3</depth>
  </size>
  <segmented>0</segmented>
  <object>
    <name>arrow_line_right</name>
    <pose>Unspecified</pose>
    <truncated>0</truncated>
    <difficult>0</difficult>
    <bndbox>
      <xmin>235</xmin>
      <ymin>529</ymin>
      <xmax>698</xmax>
      <ymax>708</ymax>
    </bndbox>
  </object>
  <object>
    <name>arrow_line_right</name>
    <pose>Unspecified</pose>
    <truncated>0</truncated>
    <difficult>0</difficult>
    <bndbox>
      <xmin>943</xmin>
      <ymin>495</ymin>
      <xmax>1718</xmax>
      <ymax>720</ymax>
    </bndbox>
  </object>
  <object>
    <name>arrow_line_right</name>
    <pose>Unspecified</pose>
    <truncated>0</truncated>
    <difficult>0</difficult>
    <bndbox>
      <xmin>1898</xmin>
      <ymin>512</ymin>
      <xmax>2589</xmax>
      <ymax>691</ymax>
    </bndbox>
  </object>
  <object>
    <name>arrow_line_right</name>
    <pose>Unspecified</pose>
    <truncated>0</truncated>
    <difficult>0</difficult>
    <bndbox>
      <xmin>268</xmin>
      <ymin>1095</ymin>
      <xmax>702</xmax>
      <ymax>1233</ymax>
    </bndbox>
  </object>
  <object>
    <name>arrow_line_right</name>
    <pose>Unspecified</pose>
    <truncated>0</truncated>
    <difficult>0</difficult>
    <bndbox>
      <xmin>1018</xmin>
      <ymin>1075</ymin>
      <xmax>1685</xmax>
      <ymax>1295</ymax>
    </bndbox>
  </object>
  <object>
    <name>arrow_line_right</name>
    <pose>Unspecified</pose>
    <truncated>0</truncated>
    <difficult>0</difficult>
    <bndbox>
      <xmin>1839</xmin>
      <ymin>1100</ymin>
      <xmax>2489</xmax>
      <ymax>1283</ymax>
    </bndbox>
  </object>
  <object>
    <name>arrow_line_right</name>
    <pose>Unspecified</pose>
    <truncated>0</truncated>
    <difficult>0</difficult>
    <bndbox>
      <xmin>235</xmin>
      <ymin>1675</ymin>
      <xmax>835</xmax>
      <ymax>1837</ymax>
    </bndbox>
  </object>
  <object>
    <name>arrow_line_right</name>
    <pose>Unspecified</pose>
    <truncated>0</truncated>
    <difficult>0</difficult>
    <bndbox>
      <xmin>968</xmin>
      <ymin>1700</ymin>
      <xmax>1689</xmax>
      <ymax>1875</ymax>
    </bndbox>
  </object>
  <object>
    <name>arrow_line_right</name>
    <pose>Unspecified</pose>
    <truncated>0</truncated>
    <difficult>0</difficult>
    <bndbox>
      <xmin>2039</xmin>
      <ymin>1687</ymin>
      <xmax>2739</xmax>
      <ymax>1891</ymax>
    </bndbox>
  </object>
  <object>
    <name>arrow_line_right</name>
    <pose>Unspecified</pose>
    <truncated>0</truncated>
    <difficult>0</difficult>
    <bndbox>
      <xmin>214</xmin>
      <ymin>2125</ymin>
      <xmax>793</xmax>
      <ymax>2279</ymax>
    </bndbox>
  </object>
  <object>
    <name>arrow_line_right</name>
    <pose>Unspecified</pose>
    <truncated>0</truncated>
    <difficult>0</difficult>
    <bndbox>
      <xmin>923</xmin>
      <ymin>2125</ymin>
      <xmax>1514</xmax>
      <ymax>2308</ymax>
    </bndbox>
  </object>
  <object>
    <name>arrow_line_right</name>
    <pose>Unspecified</pose>
    <truncated>0</truncated>
    <difficult>0</difficult>
    <bndbox>
      <xmin>1760</xmin>
      <ymin>2141</ymin>
      <xmax>2477</xmax>
      <ymax>2304</ymax>
    </bndbox>
  </object>
</annotation>