<annotation>
  <folder>train</folder>
  <filename>161.jpg</filename>
  <path>../images/161.jpg</path>
  <source>
    <database>flowchart_3b_v3</database>
  </source>
  <size>
    <width>3488</width>
    <height>4640</height>
    <depth>3</depth>
  </size>
  <segmented>0</segmented>
  <object>
    <name>arrow_line_down</name>
    <pose>Unspecified</pose>
    <truncated>0</truncated>
    <difficult>0</difficult>
    <bndbox>
      <xmin>555</xmin>
      <ymin>673</ymin>
      <xmax>740</xmax>
      <ymax>1166</ymax>
    </bndbox>
  </object>
  <object>
    <name>arrow_line_down</name>
    <pose>Unspecified</pose>
    <truncated>0</truncated>
    <difficult>0</difficult>
    <bndbox>
      <xmin>1663</xmin>
      <ymin>573</ymin>
      <xmax>1855</xmax>
      <ymax>1173</ymax>
    </bndbox>
  </object>
  <object>
    <name>arrow_line_down</name>
    <pose>Unspecified</pose>
    <truncated>0</truncated>
    <difficult>0</difficult>
    <bndbox>
      <xmin>2709</xmin>
      <ymin>527</ymin>
      <xmax>2932</xmax>
      <ymax>1166</ymax>
    </bndbox>
  </object>
  <object>
    <name>arrow_line_down</name>
    <pose>Unspecified</pose>
    <truncated>0</truncated>
    <difficult>0</difficult>
    <bndbox>
      <xmin>494</xmin>
      <ymin>1450</ymin>
      <xmax>709</xmax>
      <ymax>2120</ymax>
    </bndbox>
  </object>
  <object>
    <name>arrow_line_down</name>
    <pose>Unspecified</pose>
    <truncated>0</truncated>
    <difficult>0</difficult>
    <bndbox>
      <xmin>1563</xmin>
      <ymin>1443</ymin>
      <xmax>1770</xmax>
      <ymax>2043</ymax>
    </bndbox>
  </object>
  <object>
    <name>arrow_line_down</name>
    <pose>Unspecified</pose>
    <truncated>0</truncated>
    <difficult>0</difficult>
    <bndbox>
      <xmin>2670</xmin>
      <ymin>1420</ymin>
      <xmax>2894</xmax>
      <ymax>1996</ymax>
    </bndbox>
  </object>
  <object>
    <name>arrow_line_down</name>
    <pose>Unspecified</pose>
    <truncated>0</truncated>
    <difficult>0</difficult>
    <bndbox>
      <xmin>494</xmin>
      <ymin>2358</ymin>
      <xmax>755</xmax>
      <ymax>3081</ymax>
    </bndbox>
  </object>
  <object>
    <name>arrow_line_down</name>
    <pose>Unspecified</pose>
    <truncated>0</truncated>
    <difficult>0</difficult>
    <bndbox>
      <xmin>1517</xmin>
      <ymin>2312</ymin>
      <xmax>1824</xmax>
      <ymax>3035</ymax>
    </bndbox>
  </object>
  <object>
    <name>arrow_line_down</name>
    <pose>Unspecified</pose>
    <truncated>0</truncated>
    <difficult>0</difficult>
    <bndbox>
      <xmin>2640</xmin>
      <ymin>2273</ymin>
      <xmax>2924</xmax>
      <ymax>3050</ymax>
    </bndbox>
  </object>
  <object>
    <name>arrow_line_down</name>
    <pose>Unspecified</pose>
    <truncated>0</truncated>
    <difficult>0</difficult>
    <bndbox>
      <xmin>463</xmin>
      <ymin>3396</ymin>
      <xmax>670</xmax>
      <ymax>4243</ymax>
    </bndbox>
  </object>
  <object>
    <name>arrow_line_down</name>
    <pose>Unspecified</pose>
    <truncated>0</truncated>
    <difficult>0</difficult>
    <bndbox>
      <xmin>1555</xmin>
      <ymin>3343</ymin>
      <xmax>1770</xmax>
      <ymax>4104</ymax>
    </bndbox>
  </object>
  <object>
    <name>arrow_line_down</name>
    <pose>Unspecified</pose>
    <truncated>0</truncated>
    <difficult>0</difficult>
    <bndbox>
      <xmin>2609</xmin>
      <ymin>3304</ymin>
      <xmax>2917</xmax>
      <ymax>4104</ymax>
    </bndbox>
  </object>
</annotation>