<annotation>
  <folder>train</folder>
  <filename>315.jpg</filename>
  <path>../images/315.jpg</path>
  <source>
    <database>flowchart_3b_v3</database>
  </source>
  <size>
    <width>2448</width>
    <height>3264</height>
    <depth>3</depth>
  </size>
  <segmented>0</segmented>
  <object>
    <name>print</name>
    <pose>Unspecified</pose>
    <truncated>0</truncated>
    <difficult>0</difficult>
    <bndbox>
      <xmin>161</xmin>
      <ymin>242</ymin>
      <xmax>786</xmax>
      <ymax>612</ymax>
    </bndbox>
  </object>
  <object>
    <name>print</name>
    <pose>Unspecified</pose>
    <truncated>0</truncated>
    <difficult>0</difficult>
    <bndbox>
      <xmin>996</xmin>
      <ymin>262</ymin>
      <xmax>1591</xmax>
      <ymax>592</ymax>
    </bndbox>
  </object>
  <object>
    <name>print</name>
    <pose>Unspecified</pose>
    <truncated>0</truncated>
    <difficult>0</difficult>
    <bndbox>
      <xmin>1786</xmin>
      <ymin>212</ymin>
      <xmax>2356</xmax>
      <ymax>527</ymax>
    </bndbox>
  </object>
  <object>
    <name>print</name>
    <pose>Unspecified</pose>
    <truncated>0</truncated>
    <difficult>0</difficult>
    <bndbox>
      <xmin>71</xmin>
      <ymin>802</ymin>
      <xmax>616</xmax>
      <ymax>1137</ymax>
    </bndbox>
  </object>
  <object>
    <name>print</name>
    <pose>Unspecified</pose>
    <truncated>0</truncated>
    <difficult>0</difficult>
    <bndbox>
      <xmin>781</xmin>
      <ymin>802</ymin>
      <xmax>1511</xmax>
      <ymax>1137</ymax>
    </bndbox>
  </object>
  <object>
    <name>print</name>
    <pose>Unspecified</pose>
    <truncated>0</truncated>
    <difficult>0</difficult>
    <bndbox>
      <xmin>1701</xmin>
      <ymin>737</ymin>
      <xmax>2386</xmax>
      <ymax>1082</ymax>
    </bndbox>
  </object>
  <object>
    <name>print</name>
    <pose>Unspecified</pose>
    <truncated>0</truncated>
    <difficult>0</difficult>
    <bndbox>
      <xmin>41</xmin>
      <ymin>1467</ymin>
      <xmax>666</xmax>
      <ymax>1842</ymax>
    </bndbox>
  </object>
  <object>
    <name>print</name>
    <pose>Unspecified</pose>
    <truncated>0</truncated>
    <difficult>0</difficult>
    <bndbox>
      <xmin>831</xmin>
      <ymin>1427</ymin>
      <xmax>1501</xmax>
      <ymax>1817</ymax>
    </bndbox>
  </object>
  <object>
    <name>print</name>
    <pose>Unspecified</pose>
    <truncated>0</truncated>
    <difficult>0</difficult>
    <bndbox>
      <xmin>1716</xmin>
      <ymin>1422</ymin>
      <xmax>2406</xmax>
      <ymax>1742</ymax>
    </bndbox>
  </object>
  <object>
    <name>print</name>
    <pose>Unspecified</pose>
    <truncated>0</truncated>
    <difficult>0</difficult>
    <bndbox>
      <xmin>21</xmin>
      <ymin>2237</ymin>
      <xmax>656</xmax>
      <ymax>2722</ymax>
    </bndbox>
  </object>
  <object>
    <name>print</name>
    <pose>Unspecified</pose>
    <truncated>0</truncated>
    <difficult>0</difficult>
    <bndbox>
      <xmin>826</xmin>
      <ymin>2197</ymin>
      <xmax>1611</xmax>
      <ymax>2712</ymax>
    </bndbox>
  </object>
  <object>
    <name>print</name>
    <pose>Unspecified</pose>
    <truncated>0</truncated>
    <difficult>0</difficult>
    <bndbox>
      <xmin>1711</xmin>
      <ymin>2207</ymin>
      <xmax>2448</xmax>
      <ymax>2641</ymax>
    </bndbox>
  </object>
</annotation>