<annotation>
	<folder>images</folder>
	<filename>373.jpg</filename>
	<path>../images/373.jpg</path>
	<source>
		<database>Unknown</database>
	</source>
	<size>
		<width>3120</width>
		<height>4160</height>
		<depth>3</depth>
	</size>
	<segmented>0</segmented>
	<object>
		<name>scan</name>
		<pose>Unspecified</pose>
		<truncated>0</truncated>
		<difficult>0</difficult>
		<bndbox>
			<xmin>256</xmin>
			<ymin>313</ymin>
			<xmax>1183</xmax>
			<ymax>873</ymax>
		</bndbox>
	</object>
	<object>
		<name>scan</name>
		<pose>Unspecified</pose>
		<truncated>0</truncated>
		<difficult>0</difficult>
		<bndbox>
			<xmin>1183</xmin>
			<ymin>373</ymin>
			<xmax>2096</xmax>
			<ymax>866</ymax>
		</bndbox>
	</object>
	<object>
		<name>scan</name>
		<pose>Unspecified</pose>
		<truncated>0</truncated>
		<difficult>0</difficult>
		<bndbox>
			<xmin>2096</xmin>
			<ymin>353</ymin>
			<xmax>2996</xmax>
			<ymax>893</ymax>
		</bndbox>
	</object>
	<object>
		<name>scan</name>
		<pose>Unspecified</pose>
		<truncated>0</truncated>
		<difficult>0</difficult>
		<bndbox>
			<xmin>136</xmin>
			<ymin>1093</ymin>
			<xmax>1130</xmax>
			<ymax>1660</ymax>
		</bndbox>
	</object>
	<object>
		<name>scan</name>
		<pose>Unspecified</pose>
		<truncated>0</truncated>
		<difficult>0</difficult>
		<bndbox>
			<xmin>116</xmin>
			<ymin>1833</ymin>
			<xmax>1136</xmax>
			<ymax>2340</ymax>
		</bndbox>
	</object>
	<object>
		<name>scan</name>
		<pose>Unspecified</pose>
		<truncated>0</truncated>
		<difficult>0</difficult>
		<bndbox>
			<xmin>1156</xmin>
			<ymin>1886</ymin>
			<xmax>2163</xmax>
			<ymax>2393</ymax>
		</bndbox>
	</object>
	<object>
		<name>scan</name>
		<pose>Unspecified</pose>
		<truncated>0</truncated>
		<difficult>0</difficult>
		<bndbox>
			<xmin>2170</xmin>
			<ymin>1900</ymin>
			<xmax>3030</xmax>
			<ymax>2400</ymax>
		</bndbox>
	</object>
	<object>
		<name>scan</name>
		<pose>Unspecified</pose>
		<truncated>0</truncated>
		<difficult>0</difficult>
		<bndbox>
			<xmin>1147</xmin>
			<ymin>1145</ymin>
			<xmax>2085</xmax>
			<ymax>1701</ymax>
		</bndbox>
	</object>
	<object>
		<name>scan</name>
		<pose>Unspecified</pose>
		<truncated>0</truncated>
		<difficult>0</difficult>
		<bndbox>
			<xmin>2010</xmin>
			<ymin>1139</ymin>
			<xmax>2953</xmax>
			<ymax>1726</ymax>
		</bndbox>
	</object>
	<object>
		<name>scan</name>
		<pose>Unspecified</pose>
		<truncated>0</truncated>
		<difficult>0</difficult>
		<bndbox>
			<xmin>110</xmin>
			<ymin>2514</ymin>
			<xmax>1072</xmax>
			<ymax>3095</ymax>
		</bndbox>
	</object>
	<object>
		<name>scan</name>
		<pose>Unspecified</pose>
		<truncated>0</truncated>
		<difficult>0</difficult>
		<bndbox>
			<xmin>1060</xmin>
			<ymin>2551</ymin>
			<xmax>2047</xmax>
			<ymax>3158</ymax>
		</bndbox>
	</object>
	<object>
		<name>scan</name>
		<pose>Unspecified</pose>
		<truncated>0</truncated>
		<difficult>0</difficult>
		<bndbox>
			<xmin>2028</xmin>
			<ymin>2564</ymin>
			<xmax>2966</xmax>
			<ymax>3164</ymax>
		</bndbox>
	</object>
</annotation>
