<annotation>
  <folder>train</folder>
  <filename>462.jpg</filename>
  <path>../images/462.jpg</path>
  <source>
    <database>flowchart_3b_v3</database>
  </source>
  <size>
    <width>4224</width>
    <height>5632</height>
    <depth>3</depth>
  </size>
  <segmented>0</segmented>
  <object>
    <name>process</name>
    <pose>Unspecified</pose>
    <truncated>0</truncated>
    <difficult>0</difficult>
    <bndbox>
      <xmin>371</xmin>
      <ymin>406</ymin>
      <xmax>1407</xmax>
      <ymax>1279</ymax>
    </bndbox>
  </object>
  <object>
    <name>process</name>
    <pose>Unspecified</pose>
    <truncated>0</truncated>
    <difficult>0</difficult>
    <bndbox>
      <xmin>1916</xmin>
      <ymin>452</ymin>
      <xmax>2925</xmax>
      <ymax>1325</ymax>
    </bndbox>
  </object>
  <object>
    <name>process</name>
    <pose>Unspecified</pose>
    <truncated>0</truncated>
    <difficult>0</difficult>
    <bndbox>
      <xmin>3116</xmin>
      <ymin>525</ymin>
      <xmax>4107</xmax>
      <ymax>1279</ymax>
    </bndbox>
  </object>
  <object>
    <name>process</name>
    <pose>Unspecified</pose>
    <truncated>0</truncated>
    <difficult>0</difficult>
    <bndbox>
      <xmin>271</xmin>
      <ymin>1534</ymin>
      <xmax>1443</xmax>
      <ymax>2325</ymax>
    </bndbox>
  </object>
  <object>
    <name>process</name>
    <pose>Unspecified</pose>
    <truncated>0</truncated>
    <difficult>0</difficult>
    <bndbox>
      <xmin>1880</xmin>
      <ymin>1525</ymin>
      <xmax>3043</xmax>
      <ymax>2316</ymax>
    </bndbox>
  </object>
  <object>
    <name>process</name>
    <pose>Unspecified</pose>
    <truncated>0</truncated>
    <difficult>0</difficult>
    <bndbox>
      <xmin>3298</xmin>
      <ymin>1588</ymin>
      <xmax>4134</xmax>
      <ymax>2343</ymax>
    </bndbox>
  </object>
  <object>
    <name>process</name>
    <pose>Unspecified</pose>
    <truncated>0</truncated>
    <difficult>0</difficult>
    <bndbox>
      <xmin>307</xmin>
      <ymin>2788</ymin>
      <xmax>1352</xmax>
      <ymax>3561</ymax>
    </bndbox>
  </object>
  <object>
    <name>process</name>
    <pose>Unspecified</pose>
    <truncated>0</truncated>
    <difficult>0</difficult>
    <bndbox>
      <xmin>1707</xmin>
      <ymin>2770</ymin>
      <xmax>2862</xmax>
      <ymax>3561</ymax>
    </bndbox>
  </object>
  <object>
    <name>process</name>
    <pose>Unspecified</pose>
    <truncated>0</truncated>
    <difficult>0</difficult>
    <bndbox>
      <xmin>3098</xmin>
      <ymin>2770</ymin>
      <xmax>4080</xmax>
      <ymax>3570</ymax>
    </bndbox>
  </object>
  <object>
    <name>process</name>
    <pose>Unspecified</pose>
    <truncated>0</truncated>
    <difficult>0</difficult>
    <bndbox>
      <xmin>371</xmin>
      <ymin>4043</ymin>
      <xmax>1398</xmax>
      <ymax>4779</ymax>
    </bndbox>
  </object>
  <object>
    <name>process</name>
    <pose>Unspecified</pose>
    <truncated>0</truncated>
    <difficult>0</difficult>
    <bndbox>
      <xmin>1707</xmin>
      <ymin>4016</ymin>
      <xmax>2698</xmax>
      <ymax>4870</ymax>
    </bndbox>
  </object>
  <object>
    <name>process</name>
    <pose>Unspecified</pose>
    <truncated>0</truncated>
    <difficult>0</difficult>
    <bndbox>
      <xmin>2962</xmin>
      <ymin>4025</ymin>
      <xmax>3943</xmax>
      <ymax>4797</ymax>
    </bndbox>
  </object>
</annotation>