<annotation>
  <folder>train</folder>
  <filename>62.jpg</filename>
  <path>../images/62.jpg</path>
  <source>
    <database>flowchart_3b_v3</database>
  </source>
  <size>
    <width>2992</width>
    <height>4000</height>
    <depth>3</depth>
  </size>
  <segmented>0</segmented>
  <object>
    <name>arrow_line_right</name>
    <pose>Unspecified</pose>
    <truncated>0</truncated>
    <difficult>0</difficult>
    <bndbox>
      <xmin>189</xmin>
      <ymin>508</ymin>
      <xmax>793</xmax>
      <ymax>716</ymax>
    </bndbox>
  </object>
  <object>
    <name>arrow_line_right</name>
    <pose>Unspecified</pose>
    <truncated>0</truncated>
    <difficult>0</difficult>
    <bndbox>
      <xmin>1077</xmin>
      <ymin>529</ymin>
      <xmax>1723</xmax>
      <ymax>733</ymax>
    </bndbox>
  </object>
  <object>
    <name>arrow_line_right</name>
    <pose>Unspecified</pose>
    <truncated>0</truncated>
    <difficult>0</difficult>
    <bndbox>
      <xmin>2027</xmin>
      <ymin>525</ymin>
      <xmax>2693</xmax>
      <ymax>700</ymax>
    </bndbox>
  </object>
  <object>
    <name>arrow_line_right</name>
    <pose>Unspecified</pose>
    <truncated>0</truncated>
    <difficult>0</difficult>
    <bndbox>
      <xmin>160</xmin>
      <ymin>1183</ymin>
      <xmax>789</xmax>
      <ymax>1366</ymax>
    </bndbox>
  </object>
  <object>
    <name>arrow_line_right</name>
    <pose>Unspecified</pose>
    <truncated>0</truncated>
    <difficult>0</difficult>
    <bndbox>
      <xmin>1060</xmin>
      <ymin>1183</ymin>
      <xmax>1689</xmax>
      <ymax>1358</ymax>
    </bndbox>
  </object>
  <object>
    <name>arrow_line_right</name>
    <pose>Unspecified</pose>
    <truncated>0</truncated>
    <difficult>0</difficult>
    <bndbox>
      <xmin>2002</xmin>
      <ymin>1183</ymin>
      <xmax>2702</xmax>
      <ymax>1350</ymax>
    </bndbox>
  </object>
  <object>
    <name>arrow_line_right</name>
    <pose>Unspecified</pose>
    <truncated>0</truncated>
    <difficult>0</difficult>
    <bndbox>
      <xmin>210</xmin>
      <ymin>1904</ymin>
      <xmax>798</xmax>
      <ymax>2112</ymax>
    </bndbox>
  </object>
  <object>
    <name>arrow_line_right</name>
    <pose>Unspecified</pose>
    <truncated>0</truncated>
    <difficult>0</difficult>
    <bndbox>
      <xmin>1031</xmin>
      <ymin>1941</ymin>
      <xmax>1789</xmax>
      <ymax>2129</ymax>
    </bndbox>
  </object>
  <object>
    <name>arrow_line_right</name>
    <pose>Unspecified</pose>
    <truncated>0</truncated>
    <difficult>0</difficult>
    <bndbox>
      <xmin>2002</xmin>
      <ymin>1937</ymin>
      <xmax>2693</xmax>
      <ymax>2116</ymax>
    </bndbox>
  </object>
  <object>
    <name>arrow_line_right</name>
    <pose>Unspecified</pose>
    <truncated>0</truncated>
    <difficult>0</difficult>
    <bndbox>
      <xmin>173</xmin>
      <ymin>2883</ymin>
      <xmax>856</xmax>
      <ymax>3091</ymax>
    </bndbox>
  </object>
  <object>
    <name>arrow_line_right</name>
    <pose>Unspecified</pose>
    <truncated>0</truncated>
    <difficult>0</difficult>
    <bndbox>
      <xmin>1035</xmin>
      <ymin>2908</ymin>
      <xmax>1860</xmax>
      <ymax>3137</ymax>
    </bndbox>
  </object>
  <object>
    <name>arrow_line_right</name>
    <pose>Unspecified</pose>
    <truncated>0</truncated>
    <difficult>0</difficult>
    <bndbox>
      <xmin>2023</xmin>
      <ymin>2920</ymin>
      <xmax>2793</xmax>
      <ymax>3112</ymax>
    </bndbox>
  </object>
</annotation>